simput/__init__.py
simput/core.py
simput/domains.py
simput/filters.py
simput/handlers.py
simput/values.py
simput/pywebvue/__init__.py
simput/pywebvue/modules/__init__.py
simput/pywebvue/modules/SimPut/__init__.py
simput/pywebvue/modules/SimPut/serve/demo.html
simput/pywebvue/modules/SimPut/serve/vue-simput.common-report.html
simput/pywebvue/modules/SimPut/serve/vue-simput.common.js
simput/pywebvue/modules/SimPut/serve/vue-simput.common.js.map
simput/pywebvue/modules/SimPut/serve/vue-simput.umd-report.html
simput/pywebvue/modules/SimPut/serve/vue-simput.umd.js
simput/pywebvue/modules/SimPut/serve/vue-simput.umd.js.map
simput/pywebvue/modules/SimPut/serve/vue-simput.umd.min-report.html
simput/pywebvue/modules/SimPut/serve/vue-simput.umd.min.js
simput/pywebvue/modules/SimPut/serve/vue-simput.umd.min.js.map
simput/ui/__init__.py
simput/ui/constants.py
simput/ui/web.py
simput-2.3.0.dist-info/LICENSE
simput-2.3.0.dist-info/METADATA
simput-2.3.0.dist-info/WHEEL
simput-2.3.0.dist-info/top_level.txt
simput-2.3.0.dist-info/RECORD
